instant/__init__.py
instant/build.py
instant/cache.py
instant/codegeneration.py
instant/config.py
instant/inlining.py
instant/locking.py
instant/output.py
instant/paths.py
instant/signatures.py
instant/swig/numpy.i
instant2-2021.0.1.data/data/share/man/man1/instant-clean.1.gz
instant2-2021.0.1.data/data/share/man/man1/instant-showcache.1.gz
instant2-2021.0.1.data/scripts/instant-clean
instant2-2021.0.1.data/scripts/instant-showcache
instant2-2021.0.1.dist-info/AUTHORS
instant2-2021.0.1.dist-info/COPYING
instant2-2021.0.1.dist-info/COPYING.LESSER
instant2-2021.0.1.dist-info/LICENSE
instant2-2021.0.1.dist-info/METADATA
instant2-2021.0.1.dist-info/WHEEL
instant2-2021.0.1.dist-info/top_level.txt
instant2-2021.0.1.dist-info/RECORD
