Metadata-Version: 2.1
Name: instant2
Version: 2021.0.1
Summary: Instant Inlining of C/C++ in Python
Home-page: https://github.com/ComputationalPhysiology/instant
Author: Magne Westlie, Kent-Andre Mardal, Martin Sandve Alnes and Ilmar M. Wilbers
Author-email: fenics-dev@googlegroups.com
License: UNKNOWN
Download-URL: https://github.com/ComputationalPhysiology/instantdownloads/fenics-instant-2021.0.1.tar.gz
Platform: UNKNOWN
Classifier: Development Status :: 5 - Production/Stable
Classifier: Intended Audience :: Developers
Classifier: Intended Audience :: Science/Research
Classifier: License :: OSI Approved :: GNU Lesser General Public License v3 or later (LGPLv3+)
Classifier: Operating System :: POSIX
Classifier: Operating System :: POSIX :: Linux
Classifier: Operating System :: MacOS :: MacOS X
Classifier: Operating System :: Microsoft :: Windows
Classifier: Programming Language :: Python
Classifier: Programming Language :: Python :: 2
Classifier: Programming Language :: Python :: 2.7
Classifier: Programming Language :: Python :: 3
Classifier: Programming Language :: Python :: 3.4
Classifier: Programming Language :: Python :: 3.5
Classifier: Programming Language :: Python :: 3.6
Classifier: Topic :: Scientific/Engineering :: Mathematics
Classifier: Topic :: Software Development :: Libraries :: Python Modules
Requires-Dist: numpy
Requires-Dist: six
